eppink_utilities/__init__.py
eppink_utilities/data_utils.py
eppink_utilities/dimless_utils.py
eppink_utilities/file_utils.py
eppink_utilities/general_utils.py
eppink_utilities/heattransfer_utils.py
eppink_utilities/math_utils.py
eppink_utilities/plot_utils.py
eppink_utilities/thermo_utils.py
eppink_utilities-0.15.2.dist-info/licenses/LICENSE
eppink_utilities-0.15.2.dist-info/METADATA
eppink_utilities-0.15.2.dist-info/WHEEL
eppink_utilities-0.15.2.dist-info/top_level.txt
eppink_utilities-0.15.2.dist-info/RECORD
