Metadata-Version: 2.4
Name: eppink-utilities
Version: 0.15.2
Summary: Useful utilities for data processing, plotting, and file handling
Author: Wouter Rens Eppink
License: MIT
Project-URL: Homepage, https://github.com/someMechanicalEngineer/eppink_utilities
Project-URL: Source, https://github.com/someMechanicalEngineer/eppink_utilities
Project-URL: Tracker, https://github.com/someMechanicalEngineer/eppink_utilities/issues
Requires-Python: >=3.7
License-File: LICENSE
Requires-Dist: numpy
Requires-Dist: matplotlib
Requires-Dist: coolprop
Dynamic: license-file
